[
  {
    "rank":1,
    "team":"Ohio State",
    "abbr":"OSU",
    "wins_cum":7.0,
    "losses_cum":0.0,
    "team_id":194,
    "games_played":7,
    "rating_pred":92.7104568481,
    "spread_vs_1":0.0,
    "primary_color":"#ce1141",
    "primary_logo_url":"http:\/\/a.espncdn.com\/i\/teamlogos\/ncaa\/500\/194.png"
  },
  {
    "rank":2,
    "team":"Indiana",
    "abbr":"IU",
    "wins_cum":7.0,
    "losses_cum":0.0,
    "team_id":84,
    "games_played":7,
    "rating_pred":86.5881271362,
    "spread_vs_1":1.6413726807,
    "primary_color":"#990000",
    "primary_logo_url":"http:\/\/a.espncdn.com\/i\/teamlogos\/ncaa\/500\/84.png"
  },
  {
    "rank":3,
    "team":"Navy",
    "abbr":"NAVY",
    "wins_cum":6.0,
    "losses_cum":0.0,
    "team_id":2426,
    "games_played":6,
    "rating_pred":83.6360015869,
    "spread_vs_1":4.59349823,
    "primary_color":"#00225b",
    "primary_logo_url":"http:\/\/a.espncdn.com\/i\/teamlogos\/ncaa\/500\/2426.png"
  },
  {
    "rank":4,
    "team":"BYU",
    "abbr":"BYU",
    "wins_cum":7.0,
    "losses_cum":0.0,
    "team_id":252,
    "games_played":7,
    "rating_pred":81.4030914307,
    "spread_vs_1":6.8264083862,
    "primary_color":"#003da5",
    "primary_logo_url":"http:\/\/a.espncdn.com\/i\/teamlogos\/ncaa\/500\/252.png"
  },
  {
    "rank":5,
    "team":"Utah",
    "abbr":"UTAH",
    "wins_cum":5.0,
    "losses_cum":2.0,
    "team_id":254,
    "games_played":7,
    "rating_pred":81.2907791138,
    "spread_vs_1":6.9387207031,
    "primary_color":"#ea002a",
    "primary_logo_url":"http:\/\/a.espncdn.com\/i\/teamlogos\/ncaa\/500\/254.png"
  },
  {
    "rank":6,
    "team":"Texas A&M",
    "abbr":"TA&M",
    "wins_cum":7.0,
    "losses_cum":0.0,
    "team_id":245,
    "games_played":7,
    "rating_pred":79.9461212158,
    "spread_vs_1":8.2833786011,
    "primary_color":"#500000",
    "primary_logo_url":"http:\/\/a.espncdn.com\/i\/teamlogos\/ncaa\/500\/245.png"
  },
  {
    "rank":7,
    "team":"USC",
    "abbr":"USC",
    "wins_cum":5.0,
    "losses_cum":2.0,
    "team_id":30,
    "games_played":7,
    "rating_pred":79.5394821167,
    "spread_vs_1":8.6900177002,
    "primary_color":"#9e2237",
    "primary_logo_url":"http:\/\/a.espncdn.com\/i\/teamlogos\/ncaa\/500\/30.png"
  },
  {
    "rank":8,
    "team":"Alabama",
    "abbr":"ALA",
    "wins_cum":6.0,
    "losses_cum":1.0,
    "team_id":333,
    "games_played":7,
    "rating_pred":78.6105880737,
    "spread_vs_1":9.6189117432,
    "primary_color":"#9e1632",
    "primary_logo_url":"http:\/\/a.espncdn.com\/i\/teamlogos\/ncaa\/500\/333.png"
  },
  {
    "rank":9,
    "team":"Oklahoma",
    "abbr":"OU",
    "wins_cum":6.0,
    "losses_cum":1.0,
    "team_id":201,
    "games_played":7,
    "rating_pred":77.9032287598,
    "spread_vs_1":10.3262710571,
    "primary_color":"#a32036",
    "primary_logo_url":"http:\/\/a.espncdn.com\/i\/teamlogos\/ncaa\/500\/201.png"
  },
  {
    "rank":10,
    "team":"Notre Dame",
    "abbr":"ND",
    "wins_cum":5.0,
    "losses_cum":2.0,
    "team_id":87,
    "games_played":7,
    "rating_pred":76.8102340698,
    "spread_vs_1":11.4192657471,
    "primary_color":"#0c2340",
    "primary_logo_url":"http:\/\/a.espncdn.com\/i\/teamlogos\/ncaa\/500\/87.png"
  },
  {
    "rank":11,
    "team":"Washington",
    "abbr":"WASH",
    "wins_cum":5.0,
    "losses_cum":2.0,
    "team_id":264,
    "games_played":7,
    "rating_pred":76.0701751709,
    "spread_vs_1":12.159324646,
    "primary_color":"#33006f",
    "primary_logo_url":"http:\/\/a.espncdn.com\/i\/teamlogos\/ncaa\/500\/264.png"
  },
  {
    "rank":12,
    "team":"Texas Tech",
    "abbr":"TTU",
    "wins_cum":6.0,
    "losses_cum":1.0,
    "team_id":2641,
    "games_played":7,
    "rating_pred":75.8496170044,
    "spread_vs_1":12.3798828125,
    "primary_color":"#CC0000",
    "primary_logo_url":"http:\/\/a.espncdn.com\/i\/teamlogos\/ncaa\/500\/2641.png"
  },
  {
    "rank":13,
    "team":"Georgia",
    "abbr":"UGA",
    "wins_cum":6.0,
    "losses_cum":1.0,
    "team_id":61,
    "games_played":7,
    "rating_pred":75.6787643433,
    "spread_vs_1":12.5507354736,
    "primary_color":"#ba0c2f",
    "primary_logo_url":"http:\/\/a.espncdn.com\/i\/teamlogos\/ncaa\/500\/61.png"
  },
  {
    "rank":14,
    "team":"Missouri",
    "abbr":"MIZ",
    "wins_cum":6.0,
    "losses_cum":1.0,
    "team_id":142,
    "games_played":7,
    "rating_pred":75.1283340454,
    "spread_vs_1":13.1011657715,
    "primary_color":"#f1b82d",
    "primary_logo_url":"http:\/\/a.espncdn.com\/i\/teamlogos\/ncaa\/500\/142.png"
  },
  {
    "rank":15,
    "team":"Oregon",
    "abbr":"ORE",
    "wins_cum":6.0,
    "losses_cum":1.0,
    "team_id":2483,
    "games_played":7,
    "rating_pred":74.0740356445,
    "spread_vs_1":14.1554641724,
    "primary_color":"#007030",
    "primary_logo_url":"http:\/\/a.espncdn.com\/i\/teamlogos\/ncaa\/500\/2483.png"
  },
  {
    "rank":16,
    "team":"Ole Miss",
    "abbr":"MISS",
    "wins_cum":6.0,
    "losses_cum":1.0,
    "team_id":145,
    "games_played":7,
    "rating_pred":73.2761611938,
    "spread_vs_1":14.953338623,
    "primary_color":"#13294b",
    "primary_logo_url":"http:\/\/a.espncdn.com\/i\/teamlogos\/ncaa\/500\/145.png"
  },
  {
    "rank":17,
    "team":"Georgia Tech",
    "abbr":"GT",
    "wins_cum":7.0,
    "losses_cum":0.0,
    "team_id":59,
    "games_played":7,
    "rating_pred":73.2298355103,
    "spread_vs_1":14.9996643066,
    "primary_color":"#003057",
    "primary_logo_url":"http:\/\/a.espncdn.com\/i\/teamlogos\/ncaa\/500\/59.png"
  },
  {
    "rank":18,
    "team":"Florida State",
    "abbr":"FSU",
    "wins_cum":3.0,
    "losses_cum":4.0,
    "team_id":52,
    "games_played":7,
    "rating_pred":73.1186599731,
    "spread_vs_1":15.1108398438,
    "primary_color":"#782f40",
    "primary_logo_url":"http:\/\/a.espncdn.com\/i\/teamlogos\/ncaa\/500\/52.png"
  },
  {
    "rank":19,
    "team":"Miami",
    "abbr":"MIA",
    "wins_cum":5.0,
    "losses_cum":1.0,
    "team_id":2390,
    "games_played":6,
    "rating_pred":73.1043930054,
    "spread_vs_1":15.1251068115,
    "primary_color":"#005030",
    "primary_logo_url":"http:\/\/a.espncdn.com\/i\/teamlogos\/ncaa\/500\/2390.png"
  },
  {
    "rank":20,
    "team":"North Texas",
    "abbr":"UNT",
    "wins_cum":6.0,
    "losses_cum":1.0,
    "team_id":249,
    "games_played":7,
    "rating_pred":72.1520767212,
    "spread_vs_1":16.0774230957,
    "primary_color":"#00853E",
    "primary_logo_url":"http:\/\/a.espncdn.com\/i\/teamlogos\/ncaa\/500\/249.png"
  },
  {
    "rank":21,
    "team":"Cincinnati",
    "abbr":"CIN",
    "wins_cum":6.0,
    "losses_cum":1.0,
    "team_id":2132,
    "games_played":7,
    "rating_pred":71.809677124,
    "spread_vs_1":16.4198226929,
    "primary_color":"#E00122",
    "primary_logo_url":"http:\/\/a.espncdn.com\/i\/teamlogos\/ncaa\/500\/2132.png"
  },
  {
    "rank":22,
    "team":"Vanderbilt",
    "abbr":"VAN",
    "wins_cum":6.0,
    "losses_cum":1.0,
    "team_id":238,
    "games_played":7,
    "rating_pred":71.0845947266,
    "spread_vs_1":17.1449050903,
    "primary_color":"#866d4b",
    "primary_logo_url":"http:\/\/a.espncdn.com\/i\/teamlogos\/ncaa\/500\/238.png"
  },
  {
    "rank":23,
    "team":"Tennessee",
    "abbr":"TENN",
    "wins_cum":5.0,
    "losses_cum":2.0,
    "team_id":2633,
    "games_played":7,
    "rating_pred":70.3321075439,
    "spread_vs_1":17.8973922729,
    "primary_color":"#ff8200",
    "primary_logo_url":"http:\/\/a.espncdn.com\/i\/teamlogos\/ncaa\/500\/2633.png"
  },
  {
    "rank":24,
    "team":"Michigan",
    "abbr":"MICH",
    "wins_cum":5.0,
    "losses_cum":2.0,
    "team_id":130,
    "games_played":7,
    "rating_pred":68.9867553711,
    "spread_vs_1":19.2427444458,
    "primary_color":"#00274c",
    "primary_logo_url":"http:\/\/a.espncdn.com\/i\/teamlogos\/ncaa\/500\/130.png"
  },
  {
    "rank":25,
    "team":"Pittsburgh",
    "abbr":"PITT",
    "wins_cum":5.0,
    "losses_cum":2.0,
    "team_id":221,
    "games_played":7,
    "rating_pred":68.5642700195,
    "spread_vs_1":19.6652297974,
    "primary_color":"#003263",
    "primary_logo_url":"http:\/\/a.espncdn.com\/i\/teamlogos\/ncaa\/500\/221.png"
  }
]